{"places":[
  {
    "id": 707860,
    "name": "Hurzuf",
    "country": "UA"
  },
  {
    "id": 519188,
    "name": "Novinki",
    "country": "RU"
  },
  {
    "id": 1283378,
    "name": "Gorkhā",
    "country": "NP"
  },
  {
    "id": 1270260,
    "name": "State of Haryāna",
    "country": "IN"
  },
  {
    "id": 708546,
    "name": "Holubynka",
    "country": "UA"
  },
  {
    "id": 1283710,
    "name": "Bāgmatī Zone",
    "country": "NP"
  },
  {
    "id": 529334,
    "name": "Mar’ina Roshcha",
    "country": "RU"    
  },
  {
    "id": 1269750,
    "name": "Republic of India",
    "country": "IN"
  },
  {
    "id": 1283240,
    "name": "Kathmandu",
    "country": "NP"
  },
  {
    "id": 703363,
    "name": "Laspi",
    "country": "UA"
  },
  {
    "id": 3632308,
    "name": "Merida",
    "country": "VE"
  },
  {
    "id": 473537,
    "name": "Vinogradovo",
    "country": "RU"
  },
  {
    "id": 384848,
    "name": "Qarah Gawl al ‘Ulyā",
    "country": "IQ"
  },
  {
    "id": 569143,
    "name": "Cherkizovo",
    "country": "RU"
  },
  {
    "id": 713514,
    "name": "Alupka",
    "country": "UA"
  },
  {
    "id": 2878044,
    "name": "Lichtenrade",
    "country": "DE"
  },
  {
    "id": 464176,
    "name": "Zavety Il’icha",
    "country": "RU"
  },
  {
    "id": 295582,
    "name": "Azriqam",
    "country": "IL"
  },
  {
    "id": 1271231,
    "name": "Ghūra",
    "country": "IN"
  },
  {
    "id": 690856,
    "name": "Tyuzler",
    "country": "UA"
  },
  {
    "id": 464737,
    "name": "Zaponor’ye",
    "country": "RU"
  },
  {
    "id": 707716,
    "name": "Il’ichëvka",
    "country": "UA"
  },
  {
    "id": 697959,
    "name": "Partyzans’ke",
    "country": "UA"
  },
  {
    "id": 803611,
    "name": "Yurevichi",
    "country": "RU"
  },
  {
    "id": 614371,
    "name": "Gumist’a",
    "country": "GE"
  },
  {
    "id": 874560,
    "name": "Ptitsefabrika",
    "country": "GE"
  },
  {
    "id": 874652,
    "name": "Orekhovo",
    "country": "GE"
  },
  {
    "id": 2347078,
    "name": "Birim",
    "country": "NG"
  },
  {
    "id": 2051302,
    "name": "Priiskovyy",
    "country": "RU"
  },
  {
    "id": 563692,
    "name": "Dzhaga",
    "country": "RU"
  },
  {
    "id": 481725,
    "name": "Tret’ya Rota",
    "country": "RU"
  },
  {
    "id": 2638976,
    "name": "Ruislip",
    "country": "GB"
  },
  {
    "id": 2892705,
    "name": "Karow",
    "country": "DE"
  },
  {
    "id": 2922336,
    "name": "Gatow",
    "country": "DE"
  },
  {
    "id": 975511,
    "name": "Mkuze",
    "country": "ZA"
  },
  {
    "id": 1280737,
    "name": "Lhasa",
    "country": "CN"
  },
  {
    "id": 745042,
    "name": "İstanbul",
    "country": "TR"
  },
  {
    "id": 3496831,
    "name": "Mao",
    "country": "DO"
  },
  {
    "id": 2017370,
    "name": "Russian Federation",
    "country": "RU"
  },
  {
    "id": 2045761,
    "name": "De-Friz",
    "country": "RU"
  },
  {
    "id": 1257986,
    "name": "Rumbak",
    "country": "IN"
  },
  {
    "id": 476350,
    "name": "Vavibet",
    "country": "RU"
  },
  {
    "id": 1343000,
    "name": "Surtagān Chib",
    "country": "PK"
  },
  {
    "id": 456169,
    "name": "Rīgas Rajons",
    "country": "LV"
  },
  {
    "id": 475279,
    "name": "Verkhneye Shchekotikhino",
    "country": "RU"
  },
  {
    "id": 711349,
    "name": "Bucha",
    "country": "UA"
  },
  {
    "id": 798544,
    "name": "Republic of Poland",
    "country": "PL"
  },
  {
    "id": 3094325,
    "name": "Kuchary",
    "country": "PL"
  },  
  {
    "id": 3575514,
    "name": "Brumaire",
    "country": "KN"
  },
  {
    "id": 1861387,
    "name": "Ishikawa-ken",
    "country": "JP"
  },
  {
    "id": 1857578,
    "name": "Matoba",
    "country": "JP"
  },
  {
    "id": 1299298,
    "name": "Pya",
    "country": "MM"
  },
  {
    "id": 3256023,
    "name": "Kalanac",
    "country": "BA"
  },
  {
    "id": 2921044,
    "name": "Federal Republic of Germany",
    "country": "DE"
  },
  {
    "id": 2861876,
    "name": "Land Nordrhein-Westfalen",
    "country": "DE"
  },
  {
    "id": 802899,
    "name": "Mutaykutan",
    "country": "RU"
  },
  {
    "id": 523523,
    "name": "Nalchik",
    "country": "RU"
  },
  {
    "id": 546448,
    "name": "Kolganov",
    "country": "RU"
  },
  {
    "id": 500023,
    "name": "Rybatskiy",
    "country": "RU"
  },
  {
    "id": 2207349,
    "name": "Bellara",
    "country": "AU"
  },
  {
    "id": 7870412,
    "name": "Bartlett",
    "country": "ZA"
  },
  {
    "id": 961935,
    "name": "Rietfontein",
    "country": "ZA"
  },
  {
    "id": 3371200,
    "name": "Hardap",
    "country": "NA"
  },
  {
    "id": 1016666,
    "name": "Botswana",
    "country": "ZA"
  },
  {
    "id": 3858204,
    "name": "El Destierro",
    "country": "AR"
  },
  {
    "id": 4070245,
    "name": "Jones Crossroads",
    "country": "US"
  },
  {
    "id": 4344544,
    "name": "Vernon Parish",
    "country": "US"
  },
  {
    "id": 4215307,
    "name": "Pennick",
    "country": "US"
  },
  {
    "id": 5285039,
    "name": "Black Bear Spring",
    "country": "US"
  },
  {
    "id": 4673179,
    "name": "Bee House",
    "country": "US"
  },
  {
    "id": 6078447,
    "name": "Morden",
    "country": "CA"
  },
  {
    "id": 2201316,
    "name": "Nasirotu",
    "country": "FJ"
  },
  {
    "id": 1938756,
    "name": "Sisali",
    "country": "ID"
  },
  {
    "id": 2009359,
    "name": "Puntan",
    "country": "ID"
  },
  {
    "id": 2566086,
    "name": "Tsiémé-Mandiélé",
    "country": "CG"
  },
  {
    "id": 154733,
    "name": "Masama",
    "country": "TZ"
	},
  {
    "id": 1630349,
    "name": "Purukcahu",
    "country": "ID"
  },
  {
    "id": 2224928,
    "name": "Néméyong II",
    "country": "CM"
  },
  {
    "id": 6716279,
    "name": "Pondok Genteng",
    "country": "ID"
  },
  {
    "id": 2384618,
    "name": "Mbongoté",
    "country": "CF"
  },
  {
    "id": 378867,
    "name": "Amiling",
    "country": "SS"
  },
  {
    "id": 2230362,
    "name": "Kélkoto",
    "country": "CM"
  },
  {
    "id": 343846,
    "name": "Angetu",
    "country": "ET"
  },
  {
    "id": 370366,
    "name": "Massa",
    "country": "SD"
  },
  {
    "id": 365618,
    "name": "Tumko",
    "country": "SD"
  },
  {
    "id": 524894,
    "name": "Moskva",
    "country": "RU"
  },
  {
    "id": 1861060,
    "name": "Japan",
    "country": "JP"
  },
  {
    "id": 2130037,
    "name": "Hokkaidō",
    "country": "JP"
  },
  {
    "id": 6199126,
    "name": "Sanggrahan",
    "country": "ID"
  },
  {
    "id": 6388445,
    "name": "Karangmangle",
    "country": "ID"
  },
  {
    "id": 494806,
    "name": "Sheremetyevskiy",
    "country": "RU"
  },
  {
    "id": 467104,
    "name": "Yershovo",
    "country": "RU"
  },
  {
    "id": 462352,
    "name": "Znamenka",
    "country": "RU"
  },
  {
    "id": 2267057,
    "name": "Lisbon",
    "country": "PT"
  },
  {
    "id": 3082707,
    "name": "Walbrzych",
    "country": "PL"
  },
  {
    "id": 3091150,
    "name": "Naklo nad Notecia",
    "country": "PL"
  },
  {
    "id": 1784658,
    "name": "Zhengzhou",
    "country": "CN"
  },
  {
    "id": 7301040,
    "name": "Tonyrefail",
    "country": "GB"
  },
  {
    "id": 1348747,
    "name": "Bankra",
    "country": "IN"
  },  
  {
    "id": 524925,
    "name": "Moskovskaya Oblast’",
    "country": "RU"
  },
  {
    "id": 4047656,
    "name": "Provo",
    "country": "US"
  },
  {
    "id": 5493998,
    "name": "Tejon",
    "country": "US"
  },
  {
    "id": 1463749,
    "name": "Guliston",
    "country": "UZ"
  },
  {
    "id": 749184,
    "name": "Ciciler",
    "country": "TR"
  },
  {
    "id": 750594,
    "name": "Bilmece",
    "country": "TR"
  },
  {
    "id": 3113208,
    "name": "Provincia de Pontevedra",
    "country": "ES"
  },
  {
    "id": 2653753,
    "name": "Carmarthenshire",
    "country": "GB"
  },
  {
    "id": 658226,
    "name": "Helsinki",
    "country": "FI"
  },
  {
    "id": 2744819,
    "name": "Gemeente Wervershoof",
    "country": "NL"
  },
  {
    "id": 3017680,
    "name": "Forville",
    "country": "FR"
  },
  {
    "id": 448961,
    "name": "Tall ‘Alāwī",
    "country": "IQ"
  },
  {
    "id": 3007202,
    "name": "La Portanière",
    "country": "FR"
  },
  {
    "id": 2650353,
    "name": "East Portlemouth",
    "country": "GB"
  },
  {
    "id": 2058430,
    "name": "Whyalla",
    "country": "AU"
  },
  {
    "id": 2181258,
    "name": "Terrace End",
    "country": "NZ"
  },
  {
    "id": 2130135,
    "name": "Hashimoto",
    "country": "JP"
  },
  {
    "id": 2110681,
    "name": "Tsukuba-kenkyūgakuen-toshi",
    "country": "JP"
  },
  {
    "id": 1862845,
    "name": "Higashi-asahimachi",
    "country": "JP"
  },
  {
    "id": 1863250,
    "name": "Hanabatachō",
    "country": "JP"
  },
  {
    "id": 1852699,
    "name": "Senzaki",
    "country": "JP"
  },
  {
    "id": 1853163,
    "name": "Sakaki",
    "country": "JP"
  },
  {
    "id": 1864427,
    "name": "Daisen",
    "country": "JP"
  },
  {
    "id": 1861816,
    "name": "Ikaruga",
    "country": "JP"
  },
  {
    "id": 1857451,
    "name": "Matsuzaki",
    "country": "JP"
  },
  {
    "id": 2128894,
    "name": "Noboribetsu",
    "country": "JP"
  },
  {
    "id": 3175936,
    "name": "Grandate",
    "country": "IT"
  },
  {
    "id": 6539582,
    "name": "Biella",
    "country": "IT"
  },
  {
    "id": 6542288,
    "name": "Soverato",
    "country": "IT"
  },
  {
    "id": 6540662,
    "name": "Pinerolo",
    "country": "IT"
  },
  {
    "id": 3333225,
    "name": "Dundee City",
    "country": "GB"
  },
  {
    "id": 7290647,
    "name": "Nuneaton and Bedworth District",
    "country": "GB"
  },
  {
    "id": 7291924,
    "name": "Rhyl",
    "country": "GB"
  },
  {
    "id": 2649140,
    "name": "Foulridge",
    "country": "GB"
  },
  {
    "id": 2647062,
    "name": "Hermitage",
    "country": "GB"
  },
  {
    "id": 2648355,
    "name": "Golcar",
    "country": "GB"
  },
  {
    "id": 2636001,
    "name": "Thornbury",
    "country": "GB"
  },
  {
    "id": 510291,
    "name": "Peterhof",
    "country": "RU"
  },
  {
    "id": 518858,
    "name": "Grebnevo",
    "country": "RU"
  },
  {
    "id": 3746183,
    "name": "Centro Habana",
    "country": "CU"
  },
  {
    "id": 1014012,
    "name": "Carolina",
    "country": "ZA"
  },
  {
    "id": 3579132,
    "name": "Gustavia",
    "country": "BL"
  },
  {
    "id": 1790413,
    "name": "Xianju",
    "country": "CN"
  },
  {
    "id": 1850144,
    "name": "Tōkyō-to",
    "country": "JP"
  },
  {
    "id": 5815135,
    "name": "Washington",
    "country": "US"
  },
  {
    "id": 5391891,
    "name": "San Dimas",
    "country": "US"
  },
  {
    "id": 148251,
    "name": "Culfa",
    "country": "AZ"
  },
  {
    "id": 141668,
    "name": "Bandar Emām Khomeynī",
    "country": "IR"
  },
  {
    "id": 66108,
    "name": "Shāhrūd",
    "country": "IR"
  },
  {
    "id": 2410048,
    "name": "Bo",
    "country": "SL"
  },
  {
    "id": 1092342,
    "name": "Daché",
    "country": "KM"
  },
  {
    "id": 3719432,
    "name": "Département de l'Ouest",
    "country": "HT"
  },
  {
    "id": 6538016,
    "name": "Montescudo",
    "country": "IT"
  },
  {
    "id": 3428577,
    "name": "San Pedro",
    "country": "AR"
  },
  {
    "id": 7871309,
    "name": "Wels(Stadt)",
    "country": "AT"
  },
  {
    "id": 7839407,
    "name": "Palmerston",
    "country": "AU"
  },
  {
    "id": 147059,
    "name": "Telmankend",
    "country": "AZ"
  },
  {
    "id": 147425,
    "name": "Neftcala",
    "country": "AZ"
  },
  {
    "id": 148340,
    "name": "Pushkino",
    "country": "AZ"
  },
  {
    "id": 2784549,
    "name": "Visé",
    "country": "BE"
  },
  {
    "id": 2793079,
    "name": "Lede",
    "country": "BE"
  },
  {
    "id": 2795101,
    "name": "Ieper",
    "country": "BE"
  },
  {
    "id": 2354349,
    "name": "Titao",
    "country": "BF"
  },
  {
    "id": 6930703,
    "name": "Cascades",
    "country": "BF"
  },
  {
    "id": 3901501,
    "name": "Villazon",
    "country": "BO"
  },
  {
    "id": 6050612,
    "name": "Laval",
    "country": "CA"
  },
  {
    "id": 203717,
    "name": "Yangambi",
    "country": "CD"
  },
  {
    "id": 204283,
    "name": "Watsa",
    "country": "CD"
  },
  {
    "id": 204318,
    "name": "Wamba",
    "country": "CD"
  },
  {
    "id": 210379,
    "name": "Lusambo",
    "country": "CD"
  },
  {
    "id": 210939,
    "name": "Luebo",
    "country": "CD"
  },
  {
    "id": 211098,
    "name": "Lubao",
    "country": "CD"
  },
  {
    "id": 214575,
    "name": "Kampene",
    "country": "CD"
  },
  {
    "id": 215527,
    "name": "Kabinda",
    "country": "CD"
  },
  {
    "id": 215605,
    "name": "Kabare",
    "country": "CD"
  },
  {
    "id": 217637,
    "name": "Businga",
    "country": "CD"
  },
  {
    "id": 2311968,
    "name": "Nioki",
    "country": "CD"
  },
  {
    "id": 2312249,
    "name": "Mushie",
    "country": "CD"
  },
  {
    "id": 2313084,
    "name": "Mangai",
    "country": "CD"
  },
  {
    "id": 2314300,
    "name": "Ville de Kinshasa",
    "country": "CD"
  },
  {
    "id": 7286409,
    "name": "Luzern",
    "country": "CH"
  },
  {
    "id": 6295429,
    "name": "Fahrweid (südl. Teil)",
    "country": "CH"
  },
  {
    "id": 7286907,
    "name": "Riehen",
    "country": "CH"
  },
  {
    "id": 6291739,
    "name": "Bärenbohl",
    "country": "CH"
  },
  {
    "id": 6295642,
    "name": "Letten",
    "country": "CH"
  },
  {
    "id": 2280376,
    "name": "Touba",
    "country": "CI"
  },
  {
    "id": 2221394,
    "name": "Tonga",
    "country": "CM"
  },
  {
    "id": 3072342,
    "name": "Lahovičky",
    "country": "CZ"
  },
  {
    "id": 3064531,
    "name": "Svépravice",
    "country": "CZ"
  },
  {
    "id": 6547426,
    "name": "Wardenburg",
    "country": "DE"
  },
  {
    "id": 6553084,
    "name": "Wachtberg",
    "country": "DE"
  },
  {
    "id": 2835344,
    "name": "Schwalmtal",
    "country": "DE"
  },
  {
    "id": 7602475,
    "name": "Pfaffenhofen an der Ilm",
    "country": "DE"
  },
  {
    "id": 6553078,
    "name": "Odenthal",
    "country": "DE"
  },
  {
    "id": 6553081,
    "name": "Much",
    "country": "DE"
  },
  {
    "id": 2915013,
    "name": "Großstädteln",
    "country": "DE"
  },
  {
    "id": 6553073,
    "name": "Lindlar",
    "country": "DE"
  },
  {
    "id": 6553056,
    "name": "Kreuzau",
    "country": "DE"
  },
  {
    "id": 6557629,
    "name": "Höxter, Stadt",
    "country": "DE"
  },
  {
    "id": 2820086,
    "name": "Kreis Unna",
    "country": "DE"
  },
  {
    "id": 6553128,
    "name": "Hille",
    "country": "DE"
  },
  {
    "id": 6556314,
    "name": "Haar",
    "country": "DE"
  },
  {
    "id": 2916630,
    "name": "Grossenhain",
    "country": "DE"
  },
  {
    "id": 6553174,
    "name": "Ginsheim-Gustavsburg",
    "country": "DE"
  },
  {
    "id": 6553072,
    "name": "Engelskirchen",
    "country": "DE"
  },
  {
    "id": 6555618,
    "name": "Eggenstein-Leopoldshafen",
    "country": "DE"
  },
  {
    "id": 6553040,
    "name": "Brüggen",
    "country": "DE"
  },
  {
    "id": 2957818,
    "name": "Bönen",
    "country": "DE"
  },
  {
    "id": 3221125,
    "name": "Kreisfreie Stadt Bielefeld",
    "country": "DE"
  },
  {
    "id": 2949188,
    "name": "Bielefeld",
    "country": "DE"
  },
  {
    "id": 6555717,
    "name": "Baiersbronn",
    "country": "DE"
  },
  {
    "id": 6552854,
    "name": "Bad Zwischenahn",
    "country": "DE"
  },
  {
    "id": 6557561,
    "name": "Bad Honnef",
    "country": "DE"
  },
  {
    "id": 6553094,
    "name": "Ascheberg",
    "country": "DE"
  },
  {
    "id": 2856307,
    "name": "Ostfildern",
    "country": "DE"
  },
  {
    "id": 7602483,
    "name": "Spremberg, Stadt",
    "country": "DE"
  },
  {
    "id": 6543938,
    "name": "Høje-Taastrup Kommune",
    "country": "DK"
  },
  {
    "id": 2616011,
    "name": "Nyborg Kommune",
    "country": "DK"
  },
  {
    "id": 2618525,
    "name": "Kolding Kommune",
    "country": "DK"
  },
  {
    "id": 3495858,
    "name": "Neiba",
    "country": "DO"
  },
  {
    "id": 3496332,
    "name": "Moca",
    "country": "DO"
  },
  {
    "id": 2476412,
    "name": "el hed",
    "country": "DZ"
  },
  {
    "id": 2479183,
    "name": "Souma",
    "country": "DZ"
  },
  {
    "id": 2482939,
    "name": "Rouached",
    "country": "DZ"
  },
  {
    "id": 2483761,
    "name": "Reggane",
    "country": "DZ"
  },
  {
    "id": 2487620,
    "name": "Metlili Chaamba",
    "country": "DZ"
  },
  {
    "id": 2498775,
    "name": "El Abiodh Sidi Cheikh",
    "country": "DZ"
  },
  {
    "id": 6361023,
    "name": "Osuna",
    "country": "ES"
  },
  {
    "id": 6361010,
    "name": "Lora del Río",
    "country": "ES"
  },
  {
    "id": 6359459,
    "name": "Fuengirola",
    "country": "ES"
  },
  {
    "id": 6358465,
    "name": "Bailén",
    "country": "ES"
  },
  {
    "id": 6362958,
    "name": "Utebo",
    "country": "ES"
  },
  {
    "id": 6356273,
    "name": "Barberà del Vallès",
    "country": "ES"
  },
  {
    "id": 6359334,
    "name": "Pinto",
    "country": "ES"
  },
  {
    "id": 6533993,
    "name": "Pineda de Mar",
    "country": "ES"
  },
  {
    "id": 6534092,
    "name": "Palamós",
    "country": "ES"
  },
  {
    "id": 6359320,
    "name": "Navalcarnero",
    "country": "ES"
  },
  {
    "id": 6359308,
    "name": "Mejorada del Campo",
    "country": "ES"
  },
  {
    "id": 6356141,
    "name": "Manlleu",
    "country": "ES"
  },
  {
    "id": 6359300,
    "name": "Leganés",
    "country": "ES"
  },
  {
    "id": 6362203,
    "name": "Laguna de Duero",
    "country": "ES"
  },
  {
    "id": 6357300,
    "name": "Coruña (A)",
    "country": "ES"
  },
  {
    "id": 6361741,
    "name": "Illescas",
    "country": "ES"
  },
  {
    "id": 6356206,
    "name": "la Roca del Vallès",
    "country": "ES"
  },
  {
    "id": 6362379,
    "name": "Ermua",
    "country": "ES"
  },
  {
    "id": 6358120,
    "name": "Eibar",
    "country": "ES"
  },
  {
    "id": 6362372,
    "name": "Durango",
    "country": "ES"
  },
  {
    "id": 6359273,
    "name": "Collado Villalba",
    "country": "ES"
  },
  {
    "id": 6359266,
    "name": "Ciempozuelos",
    "country": "ES"
  },
  {
    "id": 6356068,
    "name": "Caldes de Montbui",
    "country": "ES"},
{
    "id": 6359026,
    "name": "Calahorra",
    "country": "ES"
  },
  {
    "id": 6356985,
    "name": "Benicasim/Benicàssim",
    "country": "ES"
  },
  {
    "id": 6360635,
    "name": "Realejos (Los)",
    "country": "ES"
  },
  {
    "id": 3128528,
    "name": "Basauri",
    "country": "ES"
  },
  {
    "id": 6357735,
    "name": "Lobras",
    "country": "ES"
  },
  {
    "id": 329586,
    "name": "Robit",
    "country": "ET"
  },
  {
    "id": 331180,
    "name": "Mekele",
    "country": "ET"
  },
  {
    "id": 332880,
    "name": "Kolito",
    "country": "ET"
  },
  {
    "id": 2204582,
    "name": "Lambasa",
    "country": "FJ"
  },
  {
    "id": 7626930,
    "name": "Sokehs Municipality",
    "country": "FM"
  },
  {
    "id": 6441676,
    "name": "Wittenheim",
    "country": "FR"
  },
  {
    "id": 6438569,
    "name": "Wattrelos",
    "country": "FR"
  },
  {
    "id": 6454050,
    "name": "Vitré",
    "country": "FR"
  },
  {
    "id": 6446231,
    "name": "Viry-Châtillon",
    "country": "FR"
  },
  {
    "id": 6452039,
    "name": "Villeneuve-le-Roi",
    "country": "FR"
  },
  {
    "id": 6453748,
    "name": "Vierzon",
    "country": "FR"
  },
  {
    "id": 6446218,
    "name": "Verrières-le-Buisson",
    "country": "FR"
  },
  {
    "id": 6457368,
    "name": "Arrondissement d'Antony",
    "country": "FR"
  },
  {
    "id": 6425695,
    "name": "Vallauris",
    "country": "FR"
  },
  {
    "id": 6438526,
    "name": "Tourcoing",
    "country": "FR"
  },
  {
    "id": 6446342,
    "name": "Taverny",
    "country": "FR"
  },
  {
    "id": 6446340,
    "name": "Soisy-sous-Montmorency",
    "country": "FR"
  },
  {
    "id": 6438498,
    "name": "Sin-le-Noble",
    "country": "FR"
  },
  {
    "id": 6451981,
    "name": "Sèvres",
    "country": "FR"
  },
  {
    "id": 6427088,
    "name": "Salon-de-Provence",
    "country": "FR"
  },
  {
    "id": 6455342,
    "name": "Saint-Ouen",
    "country": "FR"
  },
  {
    "id": 6441760,
    "name": "Saint-Fons",
    "country": "FR"
  },
  {
    "id": 6454369,
    "name": "Saint-Avold",
    "country": "FR"
  },
  {
    "id": 6454153,
    "name": "Rezé",
    "country": "FR"
  },
  {
    "id": 6454341,
    "name": "Pontivy",
    "country": "FR"
  },
  {
    "id": 6454014,
    "name": "Pessac",
    "country": "FR"
  },
  {
    "id": 6446184,
    "name": "Palaiseau",
    "country": "FR"
  },
  {
    "id": 6443784,
    "name": "Ozoir-la-Ferrière",
    "country": "FR"
  },
  {
    "id": 6441724,
    "name": "Oullins",
    "country": "FR"
  },
  {
    "id": 6446721,
    "name": "Mougins",
    "country": "FR"
  },
  {
    "id": 6446177,
    "name": "Morsang-sur-Orge",
    "country": "FR"
  },
  {
    "id": 6430140,
    "name": "Montélimar",
    "country": "FR"
  },
  {
    "id": 6453858,
    "name": "Montbéliard",
    "country": "FR"
  },
  {
    "id": 6452024,
    "name": "Maisons-Alfort",
    "country": "FR"
  },
  {
    "id": 6430468,
    "name": "Louviers",
    "country": "FR"
  },
  {
    "id": 6452023,
    "name": "Limeil-Brévannes",
    "country": "FR"
  },
  {
    "id": 6457185,
    "name": "Les Pavillons-sous-Bois",
    "country": "FR"
  },
  {
    "id": 6432528,
    "name": "Lattes",
    "country": "FR"
  },
  {
    "id": 6446146,
    "name": "Grigny",
    "country": "FR"
  },
  {
    "id": 6446274,
    "name": "Goussainville",
    "country": "FR"
  },
  {
    "id": 6454157,
    "name": "Gien",
    "country": "FR"
  },
  {
    "id": 6451993,
    "name": "Gagny",
    "country": "FR"
  },
  {
    "id": 6455107,
    "name": "Firminy",
    "country": "FR"
  },
  {
    "id": 6433192,
    "name": "Échirolles",
    "country": "FR"
  },
  {
    "id": 6441821,
    "name": "Décines-Charpieu",
    "country": "FR"
  },
  {
    "id": 6455404,
    "name": "Dammarie-les-Lys",
    "country": "FR"
  },
  {
    "id": 6455339,
    "name": "Colombes",
    "country": "FR"
  },
  {
    "id": 6453697,
    "name": "Cognac",
    "country": "FR"
  },
  {
    "id": 6428545,
    "name": "Chenôve",
    "country": "FR"
  },
  {
    "id": 6443604,
    "name": "Chelles",
    "country": "FR"
  },
  {
    "id": 6618272,
    "name": "Cesson-Sévigné",
    "country": "FR"
  },
  {
    "id": 3028097,
    "name": "Cayenne",
    "country": "FR"
  },
  {
    "id": 6439436,
    "name": "Carvin",
    "country": "FR"
  },
  {
    "id": 6452010,
    "name": "Bonneuil-sur-Marne",
    "country": "FR"
  },
  {
    "id": 6455331,
    "name": "Belfort",
    "country": "FR"
  },
  {
    "id": 6447202,
    "name": "Bayeux",
    "country": "FR"
  },
  {
    "id": 6613166,
    "name": "Bagnolet",
    "country": "FR"
  },
  {
    "id": 6450845,
    "name": "Autun",
    "country": "FR"
  },
  {
    "id": 6448311,
    "name": "Auch",
    "country": "FR"
  },
  {
    "id": 6451006,
    "name": "Annecy-le-Vieux",
    "country": "FR"
  },
  {
    "id": 6452610,
    "name": "Alfortville",
    "country": "FR"
  },
  {
    "id": 6455394,
    "name": "Les Ulis",
    "country": "FR"
  },
  {
    "id": 7300065,
    "name": "Yate",
    "country": "GB"
  },
  {
    "id": 7292818,
    "name": "Caia Park",
    "country": "GB"
  },
  {
    "id": 7290657,
    "name": "Worcester District",
    "country": "GB"
  },
  {
    "id": 3333222,
    "name": "Borough of Wolverhampton",
    "country": "GB"
  },
  {
    "id": 7299965,
    "name": "Winsford",
    "country": "GB"
  },
  {
    "id": 2634551,
    "name": "Welwyn Hatfield",
    "country": "GB"
  },
  {
    "id": 3333211,
    "name": "Borough of Trafford",
    "country": "GB"
  },
  {
    "id": 7290632,
    "name": "Tamworth District",
    "country": "GB"
  },
  {
    "id": 7291961,
    "name": "Wroughton",
    "country": "GB"
  },
  {
    "id": 7290571,
    "name": "Dartford District",
    "country": "GB"
  },
  {
    "id": 7290673,
    "name": "South Derbyshire District",
    "country": "GB"
  },
  {
    "id": 3333208,
    "name": "Borough of Tameside",
    "country": "GB"
  },
  {
    "id": 7291795,
    "name": "Mossley",
    "country": "GB"
  },
  {
    "id": 7294483,
    "name": "Seaham",
    "country": "GB"
  },
  {
    "id": 7295275,
    "name": "Sandown",
    "country": "GB"
  },
  {
    "id": 7297739,
    "name": "Ryton",
    "country": "GB"
  },
  {
    "id": 7290656,
    "name": "Redditch District",
    "country": "GB"
  },
  {
    "id": 7294048,
    "name": "Prestatyn",
    "country": "GB"
  },
  {
    "id": 7294693,
    "name": "Peterlee",
    "country": "GB"
  },
  {
    "id": 7301708,
    "name": "Penarth",
    "country": "GB"
  },
  {
    "id": 7292284,
    "name": "Oswestry",
    "country": "GB"
  },
  {
    "id": 7294581,
    "name": "Northwich",
    "country": "GB"
  },
  {
    "id": 2657122,
    "name": "Ards District",
    "country": "GB"
  },
  {
    "id": 2641519,
    "name": "Newtownards",
    "country": "GB"
  },
  {
    "id": 7300025,
    "name": "Newquay",
    "country": "GB"
  },
  {
    "id": 7298888,
    "name": "Nailsea",
    "country": "GB"
  },
  {
    "id": 7293862,
    "name": "Morley",
    "country": "GB"
  },
  {
    "id": 7293814,
    "name": "Mirfield",
    "country": "GB"
  },
  {
    "id": 7291605,
    "name": "Maesteg",
    "country": "GB"
  },
  {
    "id": 7296039,
    "name": "Sutton",
    "country": "GB"
  },
  {
    "id": 3333218,
    "name": "Westminster",
    "country": "GB"
  },
  {
    "id": 7295996,
    "name": "Sefton",
    "country": "GB"
  },
  {
    "id": 3333227,
    "name": "East Dunbartonshire",
    "country": "GB"
  },
  {
    "id": 3333226,
    "name": "East Ayrshire",
    "country": "GB"
  },
  {
    "id": 7296076,
    "name": "Keynsham",
    "country": "GB"
  },
  {
    "id": 7301693,
    "name": "Kempston",
    "country": "GB"
  },
  {
    "id": 7299757,
    "name": "Horwich",
    "country": "GB"
  },
  {
    "id": 7290564,
    "name": "Dacorum District",
    "country": "GB"
  },
  {
    "id": 7290687,
    "name": "Hastings District",
    "country": "GB"
  },
  {
    "id": 7291323,
    "name": "Guisborough",
    "country": "GB"
  },
  {
    "id": 7290595,
    "name": "Great Yarmouth District",
    "country": "GB"
  },
  {
    "id": 7290630,
    "name": "South Staffordshire District",
    "country": "GB"
  },
  {
    "id": 7296623,
    "name": "Goole",
    "country": "GB"
  },
  {
    "id": 7290556,
    "name": "Fareham District",
    "country": "GB"
  },
  {
    "id": 7290639,
    "name": "Epsom and Ewell District",
    "country": "GB"
  },
  {
    "id": 7290641,
    "name": "Runnymede District",
    "country": "GB"
  },
  {
    "id": 7300545,
    "name": "Ebbw Vale",
    "country": "GB"
  },
  {
    "id": 7290615,
    "name": "Broxtowe District",
    "country": "GB"
  },
  {
    "id": 7296192,
    "name": "Dunstable",
    "country": "GB"
  },
  {
    "id": 3333142,
    "name": "Derby",
    "country": "GB"
  },
  {
    "id": 7300542,
    "name": "Eccleshill",
    "country": "GB"
  },
  {
    "id": 7291971,
    "name": "Cwmbran Central",
    "country": "GB"
  },
  {
    "id": 7300082,
    "name": "Healeyfield",
    "country": "GB"
  },
  {
    "id": 7290582,
    "name": "Ribble Valley District",
    "country": "GB"
  },
  {
    "id": 7299112,
    "name": "Sodbury",
    "country": "GB"
  },
  {
    "id": 7296198,
    "name": "Brymbo",
    "country": "GB"
  },
  {
    "id": 7296060,
    "name": "Brixham",
    "country": "GB"
  },
  {
    "id": 7296000,
    "name": "Bracknell",
    "country": "GB"
  },
  {
    "id": 7291483,
    "name": "Blyth",
    "country": "GB"
  },
  {
    "id": 7299866,
    "name": "Biggleswade",
    "country": "GB"
  },
  {
    "id": 7298694,
    "name": "Berkhamsted",
    "country": "GB"
  },
  {
    "id": 7296167,
    "name": "Bathampton",
    "country": "GB"
  },
  {
    "id": 2641376,
    "name": "North Down District",
    "country": "GB"
  },
  {
    "id": 7298620,
    "name": "Bangor",
    "country": "GB"
  },
  {
    "id": 2656408,
    "name": "Banbridge District",
    "country": "GB"
  },
  {
    "id": 7292321,
    "name": "Aberystwyth",
    "country": "GB"
  },
  {
    "id": 6690583,
    "name": "Chalk Farm",
    "country": "GB"
  },
  {
    "id": 7290681,
    "name": "East Dorset District",
    "country": "GB"
  },
  {
    "id": 612366,
    "name": "Poti",
    "country": "GE"
  },
  {
    "id": 2294938,
    "name": "Tafo",
    "country": "GH"
  },
  {
    "id": 2295385,
    "name": "Shama Junction",
    "country": "GH"
  },
  {
    "id": 2295672,
    "name": "Saltpond",
    "country": "GH"
  },
  {
    "id": 2301400,
    "name": "Dunkwa",
    "country": "GH"
  },
  {
    "id": 2416443,
    "name": "Pita",
    "country": "GN"
  },
  {
    "id": 6690393,
    "name": "Sainte-Anne",
    "country": "GP"
  },
  {
    "id": 6690399,
    "name": "Pointe-à-Pitre",
    "country": "GP"
  },
  {
    "id": 6690387,
    "name": "Les Abymes",
    "country": "GP"
  },
  {
    "id": 6690413,
    "name": "Le Moule",
    "country": "GP"
  },
  {
    "id": 6690408,
    "name": "Capesterre-Belle-Eau",
    "country": "GP"
  },
  {
    "id": 8133766,
    "name": "Dimos Salamis",
    "country": "GR"
  },
  {
    "id": 8133808,
    "name": "Dimos Fyli",
    "country": "GR"
  },
  {
    "id": 3426466,
    "name": "Grytviken",
    "country": "GS"
  },
  {
    "id": 3589799,
    "name": "Municipio de San Marcos",
    "country": "GT"
  },
  {
    "id": 3595722,
    "name": "Municipio de Flores",
    "country": "GT"
  },
  {
    "id": 3600456,
    "name": "Departamento de Valle",
    "country": "HN"
  },
  {
    "id": 3716661,
    "name": "Thor",
    "country": "HT"
  },
  {
    "id": 3740016,
    "name": "Ti Port-de-Paix",
    "country": "HT"
  },
  {
    "id": 3053876,
    "name": "Csukásitanyák",
    "country": "HU"
  },
  {
    "id": 1213547,
    "name": "Tanjungbalai",
    "country": "ID"
  },
  {
    "id": 1214055,
    "name": "Reuleuet",
    "country": "ID"
  },
  {
    "id": 294622,
    "name": "Judieda Makr",
    "country": "IL"
  },
  {
    "id": 1252738,
    "name": "Yeola",
    "country": "IN"
  },
  {
    "id": 1252744,
    "name": "Yellapur",
    "country": "IN"
  },
  {
    "id": 1252773,
    "name": "Yaval",
    "country": "IN"
  },
  {
    "id": 6540553,
    "name": "Ventimiglia",
    "country": "IT"
  },
  {
    "id": 6542009,
    "name": "Savona",
    "country": "IT"
  },
  {
    "id": 6537557,
    "name": "Ruvo di Puglia",
    "country": "IT"
  },
  {
    "id": 6539485,
    "name": "Pioltello",
    "country": "IT"
  },
  {
    "id": 6536957,
    "name": "Palestrina",
    "country": "IT"
  },
  {
    "id": 6537567,
    "name": "Palagiano",
    "country": "IT"
  },
  {
    "id": 6538821,
    "name": "Pagani",
    "country": "IT"
  },
  {
    "id": 6541936,
    "name": "Orta Nova",
    "country": "IT"
  },
  {
    "id": 6540026,
    "name": "Oria",
    "country": "IT"
  },
  {
    "id": 6537554,
    "name": "Noicattaro",
    "country": "IT"
  },
  {
    "id": 6542044,
    "name": "Nettuno",
    "country": "IT"
  },
  {
    "id": 6541509,
    "name": "Negrar",
    "country": "IT"
  },
  {
    "id": 6540220,
    "name": "Mira",
    "country": "IT"
  },
  {
    "id": 6540584,
    "name": "Lissone",
    "country": "IT"
  },
  {
    "id": 6538560,
    "name": "Lastra a Signa",
    "country": "IT"
  },
  {
    "id": 6541484,
    "name": "Imperia",
    "country": "IT"
  },
  {
    "id": 6541474,
    "name": "Jesi",
    "country": "IT"
  },
  {
    "id": 6541164,
    "name": "Giugliano in Campania",
    "country": "IT"
  },
  {
    "id": 6537588,
    "name": "Galatone",
    "country": "IT"
  },
  {
    "id": 6542094,
    "name": "Gaeta",
    "country": "IT"
  },
  {
    "id": 6541853,
    "name": "Frosinone",
    "country": "IT"
  },
  {
    "id": 6538453,
    "name": "Formigine",
    "country": "IT"
  },
  {
    "id": 6541136,
    "name": "Fondi",
    "country": "IT"
  },
  {
    "id": 6540408,
    "name": "Fidenza",
    "country": "IT"
  },
  {
    "id": 6536870,
    "name": "Corciano",
    "country": "IT"
  },
  {
    "id": 6540023,
    "name": "Conversano",
    "country": "IT"
  },
  {
    "id": 6539925,
    "name": "Cittadella",
    "country": "IT"
  },
  {
    "id": 6538144,
    "name": "Bra",
    "country": "IT"
  },
  {
    "id": 6542123,
    "name": "Benevento",
    "country": "IT"
  },
  {
    "id": 6542012,
    "name": "Bareggio",
    "country": "IT"
  },
  {
    "id": 6541492,
    "name": "Arese",
    "country": "IT"
  },
  {
    "id": 6541135,
    "name": "Aprilia",
    "country": "IT"
  },
  {
    "id": 6540534,
    "name": "Anagni",
    "country": "IT"
  },
  {
    "id": 6536221,
    "name": "Spinea",
    "country": "IT"
  },
  {
    "id": 6542340,
    "name": "Volla",
    "country": "IT"
  },
  {
    "id": 3489227,
    "name": "Old Harbour",
    "country": "JM"
  },
  {
    "id": 3489297,
    "name": "New Kingston",
    "country": "JM"
  },
  {
    "id": 1859472,
    "name": "Kimiidera",
    "country": "JP"
  },
  {
    "id": 1037370,
    "name": "Mocimboa",
    "country": "MZ"
  },
  {
    "id": 2749810,
    "name": "Gemeente Noordwijkerhout",
    "country": "NL"
  },
  {
    "id": 2751688,
    "name": "Gemeente Leusden",
    "country": "NL"
  },
  {
    "id": 2753467,
    "name": "Gemeente Huizen",
    "country": "NL"
  },
  {
    "id": 2753718,
    "name": "Gemeente Hoogeveen",
    "country": "NL"
  },
  {
    "id": 2754696,
    "name": "Gemeente Heemskerk",
    "country": "NL"
  },
  {
    "id": 2759874,
    "name": "Gemeente Alphen aan den Rijn",
    "country": "NL"
  },
  {
    "id": 3160606,
    "name": "Horten",
    "country": "NO"
  },
  {
    "id": 6453374,
    "name": "Haugesund",
    "country": "NO"
  },
  {
    "id": 6453355,
    "name": "Gjøvik",
    "country": "NO"
  },
  {
    "id": 6453341,
    "name": "Ålesund",
    "country": "NO"
  },
  {
    "id": 1282635,
    "name": "Tulsipur",
    "country": "NP"
  },
  {
    "id": 6240770,
    "name": "Cambridge",
    "country": "NZ"
  },
  {
    "id": 288721,
    "name": "Bidbid",
    "country": "OM"
  },
  {
    "id": 288764,
    "name": "Bawshar",
    "country": "OM"
  },
  {
    "id": 288902,
    "name": "Badiyah",
    "country": "OM"
  },
  {
    "id": 288955,
    "name": "As Suwayq",
    "country": "OM"
  },
  {
    "id": 3691094,
    "name": "Uchiza",
    "country": "PE"
  },
  {
    "id": 7530966,
    "name": "Włocławek",
    "country": "PL"
  },
  {
    "id": 7531696,
    "name": "Świdwin",
    "country": "PL"
  },
  {
    "id": 7530961,
    "name": "Jastrzębie-Zdrój",
    "country": "PL"
  },
  {
    "id": 7532652,
    "name": "Bełchatów",
    "country": "PL"
  },
  {
    "id": 4562506,
    "name": "Aguadilla",
    "country": "PR"
  },
  {
    "id": 8014434,
    "name": "Vila Franca de Xira",
    "country": "PT"
  },
  {
    "id": 8012598,
    "name": "Ramada",
    "country": "PT"
  },
  {
    "id": 8013113,
    "name": "Almada",
    "country": "PT"
  },
  {
    "id": 8012746,
    "name": "Gueifães",
    "country": "PT"
  },
  {
    "id": 499452,
    "name": "Safonovo",
    "country": "RU"
  },
  {
    "id": 2695079,
    "name": "Lillsjönäs",
    "country": "SE"
  },
  {
    "id": 2407660,
    "name": "Koidu",
    "country": "SL"
  },
  {
    "id": 1607257,
    "name": "Prakhon Chai",
    "country": "TH"
  },
  {
    "id": 1609031,
    "name": "Changwat Lop Buri",
    "country": "TH"
  },
  {
    "id": 742902,
    "name": "Kocaali",
    "country": "TR"
  },
  {
    "id": 148942,
    "name": "Vwawa",
    "country": "TZ"
  },
  {
    "id": 4056099,
    "name": "Coffee County",
    "country": "US"
  },
  {
    "id": 4151245,
    "name": "Clay County",
    "country": "US"
  },
  {
    "id": 4155535,
    "name": "Flagler County",
    "country": "US"
  },
  {
    "id": 4158449,
    "name": "Hernando County",
    "country": "US"
  },
  {
    "id": 4174301,
    "name": "Sumter County",
    "country": "US"
  },
  {
    "id": 4196508,
    "name": "Fulton County",
    "country": "US"
  },
  {
    "id": 4191014,
    "name": "DeKalb County",
    "country": "US"
  },
  {
    "id": 4255818,
    "name": "Clark County",
    "country": "US"
  },
  {
    "id": 4310411,
    "name": "Sylvania",
    "country": "US"
  },
  {
    "id": 4287837,
    "name": "Clark County",
    "country": "US"
  },
  {
    "id": 4347820,
    "name": "Baltimore",
    "country": "US"
  },
  {
    "id": 7198188,
    "name": "Cashell Estates",
    "country": "US"
  },
  {
    "id": 4372589,
    "name": "Wakely Terrace",
    "country": "US"
  },
  {
    "id": 4406835,
    "name": "Saint Charles County",
    "country": "US"
  },
  {
    "id": 4407084,
    "name": "Saint Louis",
    "country": "US"
  },
  {
    "id": 4422178,
    "name": "Coahoma County",
    "country": "US"
  },
  {
    "id": 4431425,
    "name": "Jackson County",
    "country": "US"
  },
  {
    "id": 4481511,
    "name": "Nash County",
    "country": "US"
  },
  {
    "id": 4475520,
    "name": "Lee County",
    "country": "US"
  },
  {
    "id": 4527624,
    "name": "Warren County",
    "country": "US"
  },
  {
    "id": 4534444,
    "name": "Creek County",
    "country": "US"
  },
  {
    "id": 4592843,
    "name": "Richland County",
    "country": "US"
  },
  {
    "id": 4735729,
    "name": "Taylor County",
    "country": "US"
  },
  {
    "id": 4697444,
    "name": "Hidalgo County",
    "country": "US"
  },
  {
    "id": 4740157,
    "name": "Washington County",
    "country": "US"
  },
  {
    "id": 4739690,
    "name": "Walker County",
    "country": "US"
  },
  {
    "id": 4703071,
    "name": "Kerr County",
    "country": "US"
  },
  {
    "id": 4744106,
    "name": "Alexandria",
    "country": "US"
  },
  {
    "id": 4749005,
    "name": "Bristol",
    "country": "US"
  },
  {
    "id": 4752046,
    "name": "Charlottesville",
    "country": "US"
  },
  {
    "id": 4752215,
    "name": "Chesapeake",
    "country": "US"
  },
  {
    "id": 4753684,
    "name": "Colonial Heights",
    "country": "US"
  },
  {
    "id": 4755298,
    "name": "Danville",
    "country": "US"
  },
  {
    "id": 4758109,
    "name": "Fairfax",
    "country": "US"
  },
  {
    "id": 4760084,
    "name": "Fredericksburg",
    "country": "US"
  },
  {
    "id": 4763237,
    "name": "Harrisonburg",
    "country": "US"
  },
  {
    "id": 4764849,
    "name": "Hopewell",
    "country": "US"
  },
  {
    "id": 4771099,
    "name": "Lynchburg",
    "country": "US"
  },
  {
    "id": 4771426,
    "name": "Manassas",
    "country": "US"
  },
  {
    "id": 4776037,
    "name": "Newport News",
    "country": "US"
  },
  {
    "id": 4776242,
    "name": "Norfolk",
    "country": "US"
  },
  {
    "id": 4778642,
    "name": "Petersburg",
    "country": "US"
  },
  {
    "id": 4780019,
    "name": "Portsmouth",
    "country": "US"
  },
  {
    "id": 4780851,
    "name": "Radford",
    "country": "US"
  },
  {
    "id": 4781756,
    "name": "Richmond",
    "country": "US"
  },
  {
    "id": 4782241,
    "name": "Roanoke",
    "country": "US"
  },
  {
    "id": 4784205,
    "name": "Salem",
    "country": "US"
  },
  {
    "id": 4788160,
    "name": "Suffolk",
    "country": "US"
  },
  {
    "id": 4787467,
    "name": "Staunton",
    "country": "US"
  },
  {
    "id": 4792534,
    "name": "Waynesboro",
    "country": "US"
  },
  {
    "id": 4794134,
    "name": "Winchester",
    "country": "US"
  },
  {
    "id": 5151606,
    "name": "Cuyahoga County",
    "country": "US"
  },
  {
    "id": 4899519,
    "name": "Lee County",
    "country": "US"
  },
  {
    "id": 4898722,
    "name": "Knox County",
    "country": "US"
  },
  {
    "id": 5004681,
    "name": "Ottawa County",
    "country": "US"
  },
  {
    "id": 4985190,
    "name": "Bay County",
    "country": "US"
  },
  {
    "id": 5000477,
    "name": "Macomb County",
    "country": "US"
  },
  {
    "id": 4997130,
    "name": "Ingham County",
    "country": "US"
  },
  {
    "id": 5009706,
    "name": "Shiawassee County",
    "country": "US"
  },
  {
    "id": 5128316,
    "name": "Nassau County",
    "country": "US"
  },
  {
    "id": 6941775,
    "name": "Kings County",
    "country": "US"
  },
  {
    "id": 5113792,
    "name": "Cortland County",
    "country": "US"
  },
  {
    "id": 5112738,
    "name": "City Line",
    "country": "US"
  },
  {
    "id": 5118116,
    "name": "Fulton County",
    "country": "US"
  },
  {
    "id": 5122534,
    "name": "Jamestown",
    "country": "US"
  },
  {
    "id": 6332485,
    "name": "Queensbridge Houses",
    "country": "US"
  },
  {
    "id": 7250946,
    "name": "Carnegie Hill",
    "country": "US"
  },
  {
    "id": 5133668,
    "name": "Rensselaer County",
    "country": "US"
  },
  {
    "id": 5161640,
    "name": "Mahoning County",
    "country": "US"
  },
  {
    "id": 5151896,
    "name": "Delaware County",
    "country": "US"
  },
  {
    "id": 5145576,
    "name": "Allen County",
    "country": "US"
  },
  {
    "id": 5153362,
    "name": "Erie County",
    "country": "US"
  },
  {
    "id": 5221078,
    "name": "Bristol County",
    "country": "US"
  },
  {
    "id": 5393068,
    "name": "Santa Cruz County",
    "country": "US"
  },
  {
    "id": 5391997,
    "name": "San Francisco County",
    "country": "US"
	},
  {
    "id": 5423573,
    "name": "Grand Junction",
    "country": "US"
  },
  {
    "id": 5525886,
    "name": "Maverick County",
    "country": "US"
  },
  {
    "id": 5522430,
    "name": "Gray County",
    "country": "US"
  }
  ]}